yvoice/__init__.py
yvoice/configs/qwen2.5_1.5b_64k.json
yvoice/configs/qwen2.5_7b_32k.json
yvoice/modular/__init__.py
yvoice/modular/configuration_vibevoice.py
yvoice/modular/modeling_vibevoice.py
yvoice/modular/modeling_vibevoice_inference.py
yvoice/modular/modular_vibevoice_diffusion_head.py
yvoice/modular/modular_vibevoice_text_tokenizer.py
yvoice/modular/modular_vibevoice_tokenizer.py
yvoice/modular/streamer.py
yvoice/processor/__init__.py
yvoice/processor/vibevoice_processor.py
yvoice/processor/vibevoice_tokenizer_processor.py
yvoice/schedule/__init__.py
yvoice/schedule/dpm_solver.py
yvoice/schedule/timestep_sampler.py
yvoice/scripts/__init__.py
yvoice/scripts/convert_nnscaler_checkpoint_to_transformers.py
yvoice-0.0.4.dist-info/LICENSE
yvoice-0.0.4.dist-info/WHEEL
yvoice-0.0.4.dist-info/METADATA
yvoice-0.0.4.dist-info/RECORD
