Metadata-Version: 2.1
Name: yvoice
Version: 0.0.4
Summary: yvoice package for tts
Author-email: calcuis <info@calcu.io>
Classifier: License :: OSI Approved :: MIT License
Project-URL: Repository, https://github.com/calcuis/yvoice
